transforge/__init__.py
transforge/__main__.py
transforge/expr.py
transforge/graph.py
transforge/label.py
transforge/lang.py
transforge/list.py
transforge/namespace.py
transforge/py.typed
transforge/query.py
transforge/type.py
transforge/workflow.py
transforge/util/__init__.py
transforge/util/cli.py
transforge/util/store.py
transforge-0.2.1.dist-info/LICENSE
transforge-0.2.1.dist-info/METADATA
transforge-0.2.1.dist-info/WHEEL
transforge-0.2.1.dist-info/entry_points.txt
transforge-0.2.1.dist-info/top_level.txt
transforge-0.2.1.dist-info/RECORD
